{
  "global": {
    "25": {
      "value": "2",
      "type": "sizing"
    },
    "50": {
      "value": "4",
      "type": "sizing"
    },
    "75": {
      "value": "8",
      "type": "sizing"
    },
    "100": {
      "value": "16",
      "type": "sizing"
    },
    "125": {
      "value": "24",
      "type": "sizing"
    },
    "150": {
      "value": "36",
      "type": "sizing"
    },
    "175": {
      "value": "42",
      "type": "sizing"
    },
    "200": {
      "value": "64",
      "type": "sizing"
    },
    "none": {
      "value": "0",
      "type": "sizing"
    }
  },
  "global-dark": {},
  "$themes": [],
  "$metadata": {
    "tokenSetOrder": [
      "global",
      "global-dark"
    ]
  }
}